flake8_per_file_ignores.py
flake8_per_file_ignores-0.8.dist-info/LICENSE
flake8_per_file_ignores-0.8.dist-info/METADATA
flake8_per_file_ignores-0.8.dist-info/WHEEL
flake8_per_file_ignores-0.8.dist-info/entry_points.txt
flake8_per_file_ignores-0.8.dist-info/top_level.txt
flake8_per_file_ignores-0.8.dist-info/RECORD
