Metadata-Version: 2.1
Name: flake8-per-file-ignores
Version: 0.8
Summary: Ignore individual error codes per file with flake8
Home-page: https://github.com/snoack/flake8-per-file-ignores
Author: Sebastian Noack
Author-email: sebastian.noack@gmail.com
License: UNKNOWN
Platform: UNKNOWN
Classifier: Development Status :: 3 - Alpha
Classifier: Environment :: Console
Classifier: Intended Audience :: Developers
Classifier: License :: OSI Approved :: MIT License
Classifier: Operating System :: OS Independent
Classifier: Programming Language :: Python
Classifier: Programming Language :: Python :: 2
Classifier: Programming Language :: Python :: 3
Classifier: Topic :: Software Development :: Libraries :: Python Modules
Classifier: Topic :: Software Development :: Quality Assurance
Requires-Dist: flake8 (<3.7,>=3)
Requires-Dist: pathmatch
